LICENSE
MANIFEST.in
setup.py
tab_translation/__init__.py
tab_translation/admin.py
tab_translation/conf.py
tab_translation/static/.DS_Store
tab_translation/static/tab_translation/.DS_Store
tab_translation/static/tab_translation/css/smoothness/jquery-ui-1.10.4.custom.min.css
tab_translation/static/tab_translation/css/smoothness/images/animated-overlay.gif
tab_translation/static/tab_translation/css/smoothness/images/ui-bg_flat_0_aaaaaa_40x100.png
tab_translation/static/tab_translation/css/smoothness/images/ui-bg_flat_75_ffffff_40x100.png
tab_translation/static/tab_translation/css/smoothness/images/ui-bg_glass_55_fbf9ee_1x400.png
tab_translation/static/tab_translation/css/smoothness/images/ui-bg_glass_65_ffffff_1x400.png
tab_translation/static/tab_translation/css/smoothness/images/ui-bg_glass_75_dadada_1x400.png
tab_translation/static/tab_translation/css/smoothness/images/ui-bg_glass_75_e6e6e6_1x400.png
tab_translation/static/tab_translation/css/smoothness/images/ui-bg_glass_95_fef1ec_1x400.png
tab_translation/static/tab_translation/css/smoothness/images/ui-bg_highlight-soft_75_cccccc_1x100.png
tab_translation/static/tab_translation/css/smoothness/images/ui-icons_222222_256x240.png
tab_translation/static/tab_translation/css/smoothness/images/ui-icons_2e83ff_256x240.png
tab_translation/static/tab_translation/css/smoothness/images/ui-icons_454545_256x240.png
tab_translation/static/tab_translation/css/smoothness/images/ui-icons_888888_256x240.png
tab_translation/static/tab_translation/css/smoothness/images/ui-icons_cd0a0a_256x240.png
tab_translation/static/tab_translation/js/jquery-2.1.0.min.js
tab_translation/static/tab_translation/js/jquery-ui-1.10.4.custom.min.js
tab_translation/static/tab_translation/js/tab_translation.js
twentytab_tab_translation.egg-info/PKG-INFO
twentytab_tab_translation.egg-info/SOURCES.txt
twentytab_tab_translation.egg-info/dependency_links.txt
twentytab_tab_translation.egg-info/requires.txt
twentytab_tab_translation.egg-info/top_level.txt