Metadata-Version: 1.0
Name: twentytab-tab-translation
Version: 0.1
Summary: A django app to apply jQuery UI tab view to translated modeltranslation fields
Home-page: https://github.com/20tab/twentytab-tab-translation
Author: 20tab S.r.l.
Author-email: info@20tab.com
License: MIT License
Platform: UNKNOWN
